<?xml version="1.0" ?>
<container xmlns="http://symfony.com/schema/dic/services"
           xmlns:xsi="http://www.w3.org/2001/XMLSchema-instance"
           xsi:schemaLocation="http://symfony.com/schema/dic/services http://symfony.com/schema/dic/services/services-1.0.xsd">

    <services>
        <service id="azri_breadcrumb.breadcrumb_provider.default"
                 class="Azri\BreadcrumbBundle\Provider\BreadcrumbProvider"
                 public="true">
            <argument>%azri_breadcrumb.class.model%</argument>
            <argument>%azri_breadcrumb.class.collection%</argument>
            <argument type="service" id="router" />
            <tag name="kernel.event_listener" event="kernel.request" method="onKernelRequest" />
        </service>

        <service id="azri.breadcrumb.breadcrumb_extension"
                 class="Azri\BreadcrumbBundle\Twig\BreadcrumbExtension">
            <argument type="service" id="azri_breadcrumb.breadcrumb_provider"/>
            <argument>%azri_breadcrumb.template%</argument>
            <tag name="twig.extension"/>
        </service>

        <service id="azri_breadcrumb.routing.attach_breadcrumb_loader"
                 class="Azri\BreadcrumbBundle\Routing\BreadcrumbAttachLoader">
            <argument type="service" id="azri_breadcrumb.routing.attach_breadcrumb_loader.inner"/>
        </service>
    </services>
</container>
